ocrtest/__init__.py
ocrtest/hello.py
OCRTest_2-0.0.3.dist-info/LICENSE
OCRTest_2-0.0.3.dist-info/METADATA
OCRTest_2-0.0.3.dist-info/WHEEL
OCRTest_2-0.0.3.dist-info/top_level.txt
OCRTest_2-0.0.3.dist-info/RECORD
