Metadata-Version: 2.1
Name: OCRTest_2
Version: 0.0.3
Summary: An OCR hello package
Home-page: UNKNOWN
Author: OCR Research Lab
Author-email: <ai.r3search.lab@gmail.com>
License: UNKNOWN
Keywords: python
Platform: UNKNOWN
Classifier: Development Status :: 1 - Planning
Classifier: Intended Audience :: Developers
Classifier: Programming Language :: Python :: 3
Classifier: Operating System :: Unix
Classifier: Operating System :: MacOS :: MacOS X
Classifier: Operating System :: Microsoft :: Windows
License-File: LICENSE
